{
  "metadata": {
    "title": "Service Level Agreement - Cloud Infrastructure Support",
    "document_number": "SLA-2025-001",
    "service_provider": {
      "company": "IT-Consulting Max Mustermann",
      "name": "Max Mustermann",
      "address": {
        "street": "Musterstraße",
        "house_number": "123",
        "postal_code": "12345",
        "city": "Musterstadt"
      }
    },
    "customer": {
      "company": "TechVision GmbH",
      "name": "Thomas Weber (CTO)",
      "address": {
        "street": "Innovation Street",
        "house_number": "42",
        "postal_code": "80331",
        "city": "München"
      }
    },
    "effective_date": "01.03.2025",
    "termination_date": "28.02.2026",
    "review_period": "Quartalsweise",
    "version": "1.0",
    "status": "Aktiv",
    "created_at": {
      "date": "2025-01-25"
    },
    "show_toc": true
  },
  "content": "= Leistungsbeschreibung\n\n== Umfang der Services\n\nDer Service Provider erbringt folgende Leistungen für die AWS Cloud-Infrastruktur des Kunden:\n\n*Monitoring & Alerting:*\n- 24/7 Überwachung der Cloud-Infrastruktur\n- Proaktive Benachrichtigung bei Incidents\n- Performance Monitoring\n- Cost Monitoring und Reporting\n\n*Incident Management:*\n- Ticket-basiertes Support-System\n- Incident Response nach definierten SLAs\n- Root Cause Analysis bei kritischen Incidents\n- Post-Incident Reports\n\n*Wartung & Updates:*\n- Regelmäßige Security Updates\n- Patch Management für EC2 Instances\n- Datenbank-Wartungsfenster\n- Infrastructure-as-Code Updates\n\n*Beratung & Optimierung:*\n- Monatliche Optimierungs-Reviews\n- Cost Optimization Empfehlungen\n- Architecture Reviews\n- Best Practice Guidance\n\n= Service Level Objectives (SLOs)\n\n== Verfügbarkeit\n\n#table(\n  columns: (2fr, 1fr, 2fr),\n  [*Service*], [*SLO*], [*Messung*],\n  [Production Web Apps], [99.9%], [Uptime pro Monat],\n  [API Services], [99.95%], [Uptime pro Monat],\n  [Datenbank (RDS)], [99.95%], [Uptime pro Monat],\n  [Object Storage (S3)], [99.99%], [Availability per AWS SLA]\n)\n\n*Geplante Wartungsfenster:*\n- Jeden 1. Sonntag im Monat, 02:00-06:00 Uhr\n- Vorankündigung: Mindestens 7 Tage\n- Werden nicht auf SLO-Berechnung angerechnet\n\n== Response & Resolution Times\n\n#table(\n  columns: (1fr, 2fr, 1fr, 1fr),\n  [*Priority*], [*Definition*], [*Response*], [*Resolution*],\n  [P1 - Critical], [Production down, Datenverlust], [15 min], [4 Stunden],\n  [P2 - High], [Major Feature nicht verfügbar], [1 Stunde], [8 Stunden],\n  [P3 - Medium], [Minor Feature beeinträchtigt], [4 Stunden], [2 Werktage],\n  [P4 - Low], [Fragen, Feature Requests], [1 Werktag], [5 Werktage]\n)\n\n*Response Time:* Zeit bis zur ersten Reaktion auf ein Ticket\n*Resolution Time:* Zeit bis zur vollständigen Behebung\n\n== Performance\n\n*API Response Time:*\n- p50 (Median): < 100ms\n- p95: < 250ms\n- p99: < 500ms\n\n*Web Application Load Time:*\n- First Contentful Paint: < 1.5s\n- Time to Interactive: < 3.5s\n\n*Database Query Performance:*\n- 95% aller Queries: < 100ms\n- Komplexe Reports: < 2s\n\n= Support-Modell\n\n== Support-Zeiten\n\n*Standard Support:*\n- Montag - Freitag: 09:00 - 18:00 Uhr (MEZ)\n- Telefon, Email, Ticket-System\n\n*Emergency Support (P1):*\n- 24/7 verfügbar\n- Hotline: +49 123 456789\n- Automatische Eskalation nach 15 Minuten\n\n== Kontakt-Kanäle\n\n*Ticket-System:* https://support.it-consulting.de\n*Email:* support@it-consulting.de\n*Telefon:* +49 123 456789 (Werktags 9-18 Uhr)\n*Emergency Hotline:* +49 123 456700 (24/7 für P1)\n*Slack Channel:* #techvision-support (Business Hours)\n\n== Eskalationspfad\n\n*Level 1:* Support Engineer (Tickets P2-P4)\n*Level 2:* Senior Engineer (Tickets P1, eskalierte P2)\n*Level 3:* Lead Architect (Komplexe Architektur-Fragen)\n*Management:* Max Mustermann (Eskalation bei SLA-Verletzung)\n\n= Monitoring & Reporting\n\n== Metriken\n\n*Infrastructure Metrics:*\n- CPU, Memory, Disk Utilization\n- Network Traffic und Bandwidth\n- Error Rates und HTTP Status Codes\n- Database Connections und Slow Queries\n\n*Business Metrics:*\n- Application Response Times\n- User Sessions und Active Users\n- Transaction Volumes\n- Error Rates nach Feature\n\n== Reporting\n\n*Monatliche Reports:*\n- SLA Compliance Report\n- Incident Summary\n- Performance Trends\n- Cost Report und Optimierungen\n- Kapazitäts-Planung\n\n*Quartalsweise Reviews:*\n- Business Review Meeting\n- Architecture Review\n- SLA Review und Anpassung\n- Roadmap Planning\n\n= Verantwortlichkeiten\n\n== Service Provider Verantwortlichkeiten\n\n*Infrastruktur:*\n- AWS Account Management\n- Security Groups und IAM Policies\n- Backup und Disaster Recovery\n- Patch Management\n\n*Monitoring:*\n- 24/7 Infrastructure Monitoring\n- Alert Configuration\n- Incident Response\n\n*Dokumentation:*\n- Infrastructure-as-Code (Terraform)\n- Runbooks und Playbooks\n- Architecture Diagrams\n- Change Management Logs\n\n== Kunden-Verantwortlichkeiten\n\n*Application:*\n- Application Code und Deployments\n- Application-Level Monitoring\n- Business Logic und Features\n\n*Daten:*\n- Data Quality und Validation\n- Backup-Retention Policy\n- GDPR Compliance der Daten\n\n*Kommunikation:*\n- Rechtzeitige Meldung von Änderungen\n- Teilnahme an Quarterly Reviews\n- Feedback zu Services\n\n= Change Management\n\n== Standard Changes\n\n*Definition:* Vorab genehmigte, risikoarme Änderungen\n\n*Beispiele:*\n- Security Patches\n- Auto-Scaling Anpassungen\n- Log-Rotation Konfiguration\n\n*Prozess:*\n- Keine separate Genehmigung erforderlich\n- Automatische Benachrichtigung nach Durchführung\n\n== Normal Changes\n\n*Definition:* Planbare Änderungen mit mittlerem Risiko\n\n*Beispiele:*\n- Instance Type Änderungen\n- Neue Security Groups\n- Database Version Upgrades\n\n*Prozess:*\n- Change Request im Ticket-System\n- Genehmigung durch Kunden (48h vor Umsetzung)\n- Dokumentierter Rollback-Plan\n- Durchführung im Wartungsfenster\n\n== Emergency Changes\n\n*Definition:* Ungeplante Änderungen zur Behebung kritischer Issues\n\n*Beispiele:*\n- Security Incident Response\n- Kritische Performance-Fixes\n- Service Restoration\n\n*Prozess:*\n- Sofortige Umsetzung möglich\n- Nachträgliche Dokumentation\n- Post-Change Review innerhalb 24h\n\n= SLA-Gutschriften\n\n== Verfügbarkeits-SLA Verletzungen\n\n#table(\n  columns: (1fr, 1fr),\n  [*Verfügbarkeit*], [*Gutschrift*],\n  [< 99.9% aber ≥ 99.0%], [10% der monatlichen Gebühr],\n  [< 99.0% aber ≥ 95.0%], [25% der monatlichen Gebühr],\n  [< 95.0%], [50% der monatlichen Gebühr]\n)\n\n== Response Time SLA Verletzungen\n\nBei wiederholten Verletzungen (3+ im Monat):\n- Zusätzliche 10% Gutschrift pro Vorfall\n- Verpflichtender Process Improvement Plan\n\n*Ausnahmen (keine Gutschriften):*\n- Geplante Wartungsfenster\n- Force Majeure (AWS Outages)\n- Probleme durch Kunden-verursachte Änderungen\n- DDoS-Angriffe (außerhalb der Kontrolle)\n\n= Security & Compliance\n\n== Security Maßnahmen\n\n*Zugriffskontrolle:*\n- Multi-Factor Authentication (MFA) für alle Accounts\n- Principle of Least Privilege\n- Regelmäßige Access Reviews\n\n*Verschlüsselung:*\n- Encryption at Rest (AES-256)\n- Encryption in Transit (TLS 1.3)\n- Key Management mit AWS KMS\n\n*Monitoring:*\n- Security Monitoring mit GuardDuty\n- Config Rules für Compliance\n- CloudTrail Audit Logs\n\n== Compliance\n\n*Standards:*\n- ISO 27001 Practices\n- CIS AWS Foundations Benchmark\n- GDPR Compliance\n\n*Audits:*\n- Vierteljährliche Security Reviews\n- Penetration Tests (jährlich)\n- Compliance Reports auf Anfrage\n\n= Vertragskonditionen\n\n== Laufzeit und Kündigung\n\n*Laufzeit:* 12 Monate (01.03.2025 - 28.02.2026)\n\n*Verlängerung:* Automatisch um weitere 12 Monate, sofern nicht 3 Monate vor Ablauf gekündigt\n\n*Kündigung:* Schriftlich mit 3 Monaten Frist zum Monatsende\n\n== Preisgestaltung\n\n*Monatliche Pauschale:* 2.500 EUR (netto)\n\n*Inkludiert:*\n- 40 Stunden Support pro Monat\n- Monitoring & Alerting\n- Monatliche Reports\n- Quartalsweise Reviews\n\n*Zusatzleistungen:*\n- Weitere Support-Stunden: 95 EUR/h\n- Notfall-Support außerhalb Geschäftszeiten: 150 EUR/h\n- On-Site Support: Nach Aufwand + Reisekosten\n\n== SLA Review\n\n*Quarterly Business Reviews:*\n- Review der SLA-Metriken\n- Anpassung der Objectives bei Bedarf\n- Feedback und Verbesserungsvorschläge\n- Roadmap-Planung\n\n*Jährliche Vertrags-Review:*\n- Umfassende Service-Bewertung\n- Preisanpassungen\n- Scope-Änderungen\n- Verlängerungs-Verhandlungen"
}
